dftogsheet/__init__.py
dftogsheet/auth.py
dftogsheet/config.py
dftogsheet/sheet.py
dftogsheet-0.0.7.dist-info/LICENSE
dftogsheet-0.0.7.dist-info/METADATA
dftogsheet-0.0.7.dist-info/WHEEL
dftogsheet-0.0.7.dist-info/top_level.txt
dftogsheet-0.0.7.dist-info/RECORD
