Metadata-Version: 2.1
Name: dftogsheet
Version: 0.0.7
Summary: A Python module for writing pandas DataFrame objects directly to Google Spreadsheets
Home-page: https://github.com/wpbdry/gsheets_pkg
Author: William Dry
Author-email: wpbdry@gmail.com
License: MIT
Platform: UNKNOWN
Classifier: Programming Language :: Python :: 3
Classifier: License :: OSI Approved :: MIT License
Classifier: Operating System :: OS Independent
Requires-Dist: google-auth-oauthlib (==0.3.0)
Requires-Dist: google-api-python-client (==1.7.9)
Requires-Dist: pandas (==0.24.2)
